odoo10_addon_partner_capital-10.0.1.0.0-py2.7-nspkg.pth
odoo/addons/partner_capital/README.rst
odoo/addons/partner_capital/__init__.py
odoo/addons/partner_capital/__manifest__.py
odoo/addons/partner_capital/i18n/de.po
odoo/addons/partner_capital/i18n/es.po
odoo/addons/partner_capital/i18n/eu.po
odoo/addons/partner_capital/i18n/fi.po
odoo/addons/partner_capital/i18n/it.po
odoo/addons/partner_capital/i18n/sl.po
odoo/addons/partner_capital/models/__init__.py
odoo/addons/partner_capital/models/res_partner.py
odoo/addons/partner_capital/models/res_partner_turnover_range.py
odoo/addons/partner_capital/security/ir.model.access.csv
odoo/addons/partner_capital/static/description/icon.png
odoo/addons/partner_capital/views/res_partner_turnover_range_view.xml
odoo/addons/partner_capital/views/res_partner_view.xml
odoo10_addon_partner_capital-10.0.1.0.0.dist-info/DESCRIPTION.rst
odoo10_addon_partner_capital-10.0.1.0.0.dist-info/METADATA
odoo10_addon_partner_capital-10.0.1.0.0.dist-info/RECORD
odoo10_addon_partner_capital-10.0.1.0.0.dist-info/WHEEL
odoo10_addon_partner_capital-10.0.1.0.0.dist-info/metadata.json
odoo10_addon_partner_capital-10.0.1.0.0.dist-info/namespace_packages.txt
odoo10_addon_partner_capital-10.0.1.0.0.dist-info/top_level.txt
