Metadata-Version: 2.0
Name: odoo10-addon-partner-capital
Version: 10.0.1.0.0
Summary: Partners Capital
Home-page: https://www.tecnativa.com
Author: Antiun Ingeniería S.L., Tecnativa, Odoo Community Association (OCA)
Author-email: support@odoo-community.org
License: UNKNOWN
Platform: UNKNOWN
Classifier: Programming Language :: Python :: 2.7
Classifier: Framework :: Odoo
Requires-Dist: odoo (<10.1dev,>=10.0)
